moticreader/__init__.py
moticreader/pyramid.py
moticreader/trans.py
moticreader-0.3.dist-info/LICENSE
moticreader-0.3.dist-info/METADATA
moticreader-0.3.dist-info/WHEEL
moticreader-0.3.dist-info/top_level.txt
moticreader-0.3.dist-info/RECORD
